shoggoth/__init__.py
shoggoth/__main__.py
shoggoth/arkham_build.py
shoggoth/card.py
shoggoth/card_file_handler.py
shoggoth/dialogs.py
shoggoth/editors.py
shoggoth/encounter_editor.py
shoggoth/encounter_set.py
shoggoth/export_helpers.py
shoggoth/face_editors.py
shoggoth/file_monitor.py
shoggoth/files.py
shoggoth/floating_label_widget.py
shoggoth/goto_dialog.py
shoggoth/guide.py
shoggoth/guide_editor.py
shoggoth/location_view.py
shoggoth/main_qt.py
shoggoth/main_window.py
shoggoth/pdf_exporter.py
shoggoth/preview_widget.py
shoggoth/project.py
shoggoth/project_editor.py
shoggoth/renderer.py
shoggoth/rich_text.py
shoggoth/run.py
shoggoth/settings.py
shoggoth/strange_eons.py
shoggoth/strange_eons_dialog.py
shoggoth/strange_eons_parser.py
shoggoth/text_editor.py
shoggoth/tool.py
shoggoth/tree_context_menu.py
shoggoth/tts_lib.py
shoggoth/updater.py
shoggoth-0.1.7.dist-info/METADATA
shoggoth-0.1.7.dist-info/WHEEL
shoggoth-0.1.7.dist-info/entry_points.txt
shoggoth-0.1.7.dist-info/licenses/LICENSE
shoggoth-0.1.7.dist-info/RECORD
