Metadata-Version: 2.4
Name: shoggoth
Version: 0.1.7
Summary: A card creator for Arkham Horror: The Card Game
Project-URL: Homepage, https://github.com/tokeeto/shoggoth
Project-URL: Issues, https://github.com/tokeeto/shoggoth/issues
Author-email: Toke Ivø <toke.ivo@gmail.com>
License-Expression: GPL-3.0-or-later
License-File: LICENSE
Classifier: Operating System :: OS Independent
Classifier: Programming Language :: Python :: 3
Requires-Python: >=3.11
Requires-Dist: cairosvg>=2.8.2
Requires-Dist: filedialpy>=1.3.3
Requires-Dist: jpype1>=1.6.0
Requires-Dist: numpy>=2.2.4
Requires-Dist: pillow-jxl-plugin>=1.3.4
Requires-Dist: pillow>=11.2.1
Requires-Dist: platformdirs>=4.3.8
Requires-Dist: pygments>=2.19.1
Requires-Dist: pymupdf>=1.26.5
Requires-Dist: pyside6>=6.10.1
Requires-Dist: requests>=2.32.5
Requires-Dist: watchdog>=6.0.0
Requires-Dist: weasyprint>=66.0
